CHANGES.md
LICENSE
MANIFEST.in
README.md
setup.py
freebible/__init__.py
freebible/__version__.py
freebible/helpers.py
freebible/model.py
freebible/tools.py
freebible.egg-info/PKG-INFO
freebible.egg-info/SOURCES.txt
freebible.egg-info/dependency_links.txt
freebible.egg-info/requires.txt
freebible.egg-info/top_level.txt
freebible/data/__init__.py
freebible/data/kougo/kougo.txt.gz
freebible/data/web/key_abbreviations_english.csv.gz
freebible/data/web/key_english.csv.gz
freebible/data/web/key_genre_english.csv.gz
freebible/data/web/t_web.csv.gz
freebible/parsers/__init__.py
freebible/parsers/kougo.py
freebible/parsers/web.py
test/test_helpers.py
test/test_model.py
test/test_parsers.py