Metadata-Version: 2.1
Name: freebible
Version: 0.1a8
Summary: A bible processing toolkit with free bible data for Python
Home-page: https://github.com/neocl/freebible
Author: Le Tuan Anh
Author-email: tuananh.ke@gmail.com
License: MIT License
Project-URL: Bug Tracker, https://github.com/neocl/freebible/issues
Project-URL: Source Code, https://github.com/neocl/freebible/
Keywords: free holy bible nlp
Platform: any
Classifier: Programming Language :: Python
Classifier: Development Status :: 2 - Pre-Alpha
Classifier: Natural Language :: English
Classifier: Natural Language :: Japanese
Classifier: Natural Language :: Indonesian
Classifier: Environment :: Plugins
Classifier: Intended Audience :: Science/Research
Classifier: Intended Audience :: Developers
Classifier: Intended Audience :: Religion
Classifier: License :: OSI Approved :: MIT License
Classifier: Operating System :: OS Independent
Classifier: Topic :: Religion
Classifier: Topic :: Text Processing
Classifier: Topic :: Software Development :: Libraries :: Python Modules
